Metadata-Version: 2.1
Name: odoo13-addon-sale-stock-available-to-promise-release-cutoff
Version: 13.0.1.0.1.dev5
Summary: Cutoff management with respect to stock availability
Home-page: https://github.com/OCA/wms
Author: Camptocamp,Odoo Community Association (OCA)
Author-email: support@odoo-community.org
License: LGPL-3
Platform: UNKNOWN
Classifier: Programming Language :: Python
Classifier: Framework :: Odoo
Classifier: Framework :: Odoo :: 13.0
Classifier: License :: OSI Approved :: GNU Lesser General Public License v3 (LGPLv3)
Requires-Python: >=3.5
Requires-Dist: odoo13-addon-sale-cutoff-time-delivery
Requires-Dist: odoo13-addon-sale-stock-available-to-promise-release
Requires-Dist: odoo <13.1dev,>=13.0a
